kore_plugins_celery/__init__.py
kore_plugins_celery/plugins/__init__.py
kore_plugins_celery/plugins/celery.py
kore_plugins_celery-0.0.5.dist-info/DESCRIPTION.rst
kore_plugins_celery-0.0.5.dist-info/METADATA
kore_plugins_celery-0.0.5.dist-info/RECORD
kore_plugins_celery-0.0.5.dist-info/WHEEL
kore_plugins_celery-0.0.5.dist-info/entry_points.txt
kore_plugins_celery-0.0.5.dist-info/metadata.json
kore_plugins_celery-0.0.5.dist-info/top_level.txt
