Metadata-Version: 2.0
Name: kore-plugins-celery
Version: 0.0.5
Summary: UNKNOWN
Home-page: https://github.com/kore-plugins/kore-plugins-celery
Author: Artur Maciąg
Author-email: maciag.artur@gmail.com
License: UNKNOWN
Platform: UNKNOWN
Classifier: Intended Audience :: Developers
Classifier: Programming Language :: Python :: 2.7
Classifier: Programming Language :: Python :: 3.4
Classifier: Programming Language :: Python :: 3.6
Classifier: Topic :: Software Development :: Libraries
Requires-Dist: celery (>=4.0.2)
Requires-Dist: kore (>=0.0.3)
Requires-Dist: kore-shell
